summer/__init__.py
summer/cli.py
summer/utils.py
summer_days-1.1.0.dist-info/LICENSE
summer_days-1.1.0.dist-info/METADATA
summer_days-1.1.0.dist-info/WHEEL
summer_days-1.1.0.dist-info/entry_points.txt
summer_days-1.1.0.dist-info/top_level.txt
summer_days-1.1.0.dist-info/RECORD
