Metadata-Version: 2.1
Name: summer-days
Version: 1.1.0
Summary: A Python package to get weather reports for any location.
Home-page: https://github.com/
Author: Code Vision
Author-email: codevision.source@gmail.com
License: MIT
Platform: UNKNOWN
Classifier: License :: OSI Approved :: MIT License
Classifier: Programming Language :: Python :: 3
Classifier: Programming Language :: Python :: 3.7
Requires-Dist: requests
